translation_god-1.0.2.dist-info/METADATA
translation_god-1.0.2.dist-info/WHEEL
translation_god-1.0.2.dist-info/entry_points.txt
translation_god/.ruff_cache/.gitignore
translation_god/.ruff_cache/0.4.1/14417344667987702384
translation_god/.ruff_cache/CACHEDIR.TAG
translation_god/__init__.py
translation_god/answer_parser.py
translation_god/chatgpt_service.py
translation_god/config.py
translation_god/helpers.py
translation_god/main.py
translation_god/options_parser.py
translation_god/pick_json.py
translation_god-1.0.2.dist-info/RECORD
