Metadata-Version: 2.1
Name: translation_god
Version: 1.0.2
Summary: A translation tool based ChatGPT
Author-Email: zayfen <zhangyunfeng0101@gmail.com>
Classifier: Development Status :: 4 - Beta
Classifier: Intended Audience :: Developers
Classifier: License :: OSI Approved :: MIT License
Classifier: Programming Language :: Python :: 3.10
Classifier: Programming Language :: Python :: 3.11
Classifier: Programming Language :: Python :: 3.12
Classifier: Programming Language :: Python :: 3.5
Classifier: Programming Language :: Python :: 3.6
Classifier: Programming Language :: Python :: 3.7
Classifier: Programming Language :: Python :: 3.8
Classifier: Programming Language :: Python :: 3.9
Classifier: Topic :: Utilities
Project-URL: Homepage, https://github.com/zayfen/TranslationGod
Requires-Python: >=3.5
Requires-Dist: annotated-types==0.6.0
Requires-Dist: anyio==3.7.1
Requires-Dist: attrs==23.1.0
Requires-Dist: certifi==2023.11.17
Requires-Dist: distro==1.8.0
Requires-Dist: esprima==4.0.1
Requires-Dist: et-xmlfile==1.1.0
Requires-Dist: h11==0.14.0
Requires-Dist: httpcore==1.0.2
Requires-Dist: httpx==0.25.2
Requires-Dist: idna==3.4
Requires-Dist: inflection==0.5.1
Requires-Dist: iniconfig==2.0.0
Requires-Dist: jsonschema==4.20.0
Requires-Dist: jsonschema-specifications==2023.11.1
Requires-Dist: numpy==1.26.2
Requires-Dist: openai==1.3.5
Requires-Dist: openapi==1.1.0
Requires-Dist: openpyxl==3.1.2
Requires-Dist: packaging==23.2
Requires-Dist: pandas==2.1.3
Requires-Dist: pluggy==1.3.0
Requires-Dist: pydantic==2.5.2
Requires-Dist: pydantic-core==2.14.5
Requires-Dist: pytest==7.4.3
Requires-Dist: python-dateutil==2.8.2
Requires-Dist: pytz==2023.3.post1
Requires-Dist: referencing==0.31.0
Requires-Dist: rpds-py==0.13.1
Requires-Dist: six==1.16.0
Requires-Dist: sniffio==1.3.0
Requires-Dist: tqdm==4.66.1
Requires-Dist: typing-extensions==4.8.0
Requires-Dist: tzdata==2023.3
Requires-Dist: XlsxWriter==3.1.9
